[
  {
    "name": "Торстейн",
    "status": "unknown",
    "race": "Тангат",
    "class": "Воин | Шаман",
    "archetype": "Чемпион | —",
    "portrait": "assets/Торстейн.png",
    "urv": 0,
    "hp": 0,
    "brn": 0,
    "stats": {
      "СИЛ": 0,
      "ИНТ": 0,
      "ЛОВ": 0,
      "МУД": 0,
      "ВЫН": 0,
      "ХАР": 0
    }
  },
  {
    "name": "Вук",
    "status": "dead",
    "race": "Ойрхонец",
    "class": "Друид",
    "archetype": "Круг инстинктов",
    "portrait": "assets/Вук.png",
    "urv": 0,
    "hp": 0,
    "brn": 0,
    "stats": {
      "СИЛ": 0,
      "ИНТ": 0,
      "ЛОВ": 0,
      "МУД": 0,
      "ВЫН": 0,
      "ХАР": 0
    }
  },
  {
    "name": "Драгана",
    "status": "unknown",
    "race": "Сарвид",
    "class": "Чародей",
    "archetype": "Духовный сосуд",
    "portrait": "assets/Драгана.png",
    "urv": 0,
    "hp": 0,
    "brn": 0,
    "stats": {
      "СИЛ": 0,
      "ИНТ": 0,
      "ЛОВ": 0,
      "МУД": 0,
      "ВЫН": 0,
      "ХАР": 0
    }
  },
  {
    "name": "Анагор",
    "status": "dead",
    "race": "Эванкил",
    "class": "Паладин",
    "archetype": "Клятва молчания",
    "portrait": "assets/Анагор.png",
    "urv": 0,
    "hp": 0,
    "brn": 0,
    "stats": {
      "СИЛ": 0,
      "ИНТ": 0,
      "ЛОВ": 0,
      "МУД": 0,
      "ВЫН": 0,
      "ХАР": 0
    }
  },
  {
    "name": "Кю",
    "status": "unknown",
    "race": "Сунстей",
    "class": "Бард",
    "archetype": "Коллегия кукловодов",
    "portrait": "assets/Кю.png",
    "urv": 0,
    "hp": 0,
    "brn": 0,
    "stats": {
      "СИЛ": 0,
      "ИНТ": 0,
      "ЛОВ": 0,
      "МУД": 0,
      "ВЫН": 0,
      "ХАР": 0
    }
  },
  {
    "name": "Сахаян",
    "status": "dead",
    "race": "Эванкил",
    "class": "Шаман",
    "archetype": "Руны Хаада",
    "portrait": "assets/Сахаян.png",
    "urv": 0,
    "hp": 0,
    "brn": 0,
    "stats": {
      "СИЛ": 0,
      "ИНТ": 0,
      "ЛОВ": 0,
      "МУД": 0,
      "ВЫН": 0,
      "ХАР": 0
    }
  },
  {
    "name": "Лорат",
    "status": "unknown",
    "race": "Хагас-бако",
    "class": "Монах",
    "archetype": "Путь Акуна",
    "portrait": "assets/Лорат.png",
    "urv": 0,
    "hp": 0,
    "brn": 0,
    "stats": {
      "СИЛ": 0,
      "ИНТ": 0,
      "ЛОВ": 0,
      "МУД": 0,
      "ВЫН": 0,
      "ХАР": 0
    }
  },
  {
    "name": "Агата Дюваль",
    "status": "dead",
    "race": "Человек",
    "class": "Изобретатель",
    "archetype": "Артиллерист",
    "portrait": "assets/Агата.png",
    "urv": 0,
    "hp": 0,
    "brn": 0,
    "stats": {
      "СИЛ": 0,
      "ИНТ": 0,
      "ЛОВ": 0,
      "МУД": 0,
      "ВЫН": 0,
      "ХАР": 0
    }
  },
  {
    "name": "Азандей",
    "status": "unknown",
    "race": "Сарвид",
    "class": "Колдун",
    "archetype": "Первичный",
    "portrait": "assets/Азандей.png",
    "urv": 0,
    "hp": 0,
    "brn": 0,
    "stats": {
      "СИЛ": 0,
      "ИНТ": 0,
      "ЛОВ": 0,
      "МУД": 0,
      "ВЫН": 0,
      "ХАР": 0
    }
  },
  {
    "name": "Гург Каури Егу",
    "status": "dead",
    "race": "Нокар",
    "class": "Варвар",
    "archetype": "Путь неутолимого голода",
    "portrait": "assets/Гург.png",
    "urv": 0,
    "hp": 0,
    "brn": 0,
    "stats": {
      "СИЛ": 0,
      "ИНТ": 0,
      "ЛОВ": 0,
      "МУД": 0,
      "ВЫН": 0,
      "ХАР": 0
    }
  },
  {
    "name": "Крив",
    "status": "dead",
    "race": "Сарвид",
    "class": "Шаман",
    "archetype": "Путь кровавых ритуалов Айзы",
    "portrait": "assets/Крив.png",
    "urv": 0,
    "hp": 0,
    "brn": 0,
    "stats": {
      "СИЛ": 0,
      "ИНТ": 0,
      "ЛОВ": 0,
      "МУД": 0,
      "ВЫН": 0,
      "ХАР": 0
    }
  },
  {
    "name": "Ветвистая",
    "status": "unknown",
    "race": "Занчин",
    "class": "Следопыт",
    "archetype": "Хранитель роя",
    "portrait": "assets/Ветвистая.png",
    "urv": 0,
    "hp": 0,
    "brn": 0,
    "stats": {
      "СИЛ": 0,
      "ИНТ": 0,
      "ЛОВ": 0,
      "МУД": 0,
      "ВЫН": 0,
      "ХАР": 0
    }
  },
  {
    "name": "Асгхан",
    "status": "unknown",
    "race": "Эванкил",
    "class": "Тамак",
    "archetype": "Король берадов",
    "portrait": "assets/Асгхан.png",
    "urv": 0,
    "hp": 0,
    "brn": 0,
    "stats": {
      "СИЛ": 0,
      "ИНТ": 0,
      "ЛОВ": 0,
      "МУД": 0,
      "ВЫН": 0,
      "ХАР": 0
    }
  },
  {
    "name": "Саяра",
    "status": "unknown",
    "race": "Эванкил",
    "class": "Плут",
    "archetype": "Заккирийский мерзавец",
    "portrait": "assets/Саяра.png",
    "urv": 0,
    "hp": 0,
    "brn": 0,
    "stats": {
      "СИЛ": 0,
      "ИНТ": 0,
      "ЛОВ": 0,
      "МУД": 0,
      "ВЫН": 0,
      "ХАР": 0
    }
  }
]
